{
  "experience": "105",
  "degree": "204",
  "areaBusiness": "110115",
  "total": 8,
  "catch_total": 8,
  "jobs": [
    {
      "job_name": "前端开发专家",
      "areaBusiness": "北京·大兴区·亦庄",
      "salary": "30-50K·19薪",
      "experience": "3-5年",
      "degree": "硕士",
      "company_name": "京东集团",
      "company_logo": "https://img.bosszhipin.com/beijin/mcs/bar/20191129/3cdf5ba2149e309b38868b62ae9c22cabe1bd4a3bd2a63f070bdbdada9aad826.jpg?x-oss-process=image/resize,w_100,limit_0",
      "company_kind": "电子商务",
      "company_listing": "已上市",
      "company_size": "10000人以上",
      "boss_job": "",
      "key_words": [],
      "boss_active_time": "",
      "detail": ""
    },
    {
      "job_name": "全栈工程师",
      "areaBusiness": "北京·大兴区·德茂桥",
      "salary": "13-18K",
      "experience": "3-5年",
      "degree": "硕士",
      "company_name": "灵犀医疗",
      "company_logo": "https://img.bosszhipin.com/beijin/upload/com/workfeel/20211207/7bf6f160950405e90a92b46b596c9a2659f5e86372742c41f13abf65dc231fd7dbb6aef0532b75dd.jpg?x-oss-process=image/resize,w_100,limit_0",
      "company_kind": "医疗健康",
      "company_listing": "天使轮",
      "company_size": "100-499人",
      "boss_job": "",
      "key_words": [],
      "boss_active_time": "",
      "detail": ""
    },
    {
      "job_name": "数字电路设计工程师",
      "areaBusiness": "北京·大兴区·亦庄",
      "salary": "20-40K·13薪",
      "experience": "3-5年",
      "degree": "硕士",
      "company_name": "北京显芯科技有限公司",
      "company_logo": "https://img.bosszhipin.com/beijin/mcs/chatphoto/20200713/f2ac5b69677f7a5b2f67b6f6afacefea7c52c67b3f509c2b56ead80186d5f718_s.jpg?x-oss-process=image/resize,w_100,limit_0",
      "company_kind": "半导体/芯片",
      "company_listing": "B轮",
      "company_size": "20-99人",
      "boss_job": "",
      "key_words": [],
      "boss_active_time": "",
      "detail": ""
    },
    {
      "job_name": "遗传咨询主管",
      "areaBusiness": "北京·大兴区·亦庄",
      "salary": "15-25K",
      "experience": "3-5年",
      "degree": "硕士",
      "company_name": "安诺优达基因科技",
      "company_logo": "https://img.bosszhipin.com/beijin/mcs/chatphoto/20180412/7edfc7a4cc5c70339ee9c36792c47fbb.png?x-oss-process=image/resize,w_100,limit_0",
      "company_kind": "医疗健康",
      "company_listing": "C轮",
      "company_size": "500-999人",
      "boss_job": "",
      "key_words": [],
      "boss_active_time": "",
      "detail": ""
    },
    {
      "job_name": "产品经理（北京）",
      "areaBusiness": "北京·大兴区·亦庄",
      "salary": "20-35K",
      "experience": "3-5年",
      "degree": "硕士",
      "company_name": "多赢医学集团",
      "company_logo": "https://img.bosszhipin.com/beijin/icon/894ce6fa7e58d64d57e7f22d2f3a9d18afa7fcceaa24b8ea28f56f1bb14732c0.png?x-oss-process=image/resize,w_100,limit_0",
      "company_kind": "医疗服务",
      "company_listing": "天使轮",
      "company_size": "20-99人",
      "boss_job": "",
      "key_words": [],
      "boss_active_time": "",
      "detail": ""
    },
    {
      "job_name": "R4010559 Software Engineer 图像重建",
      "areaBusiness": "北京·大兴区·亦庄",
      "salary": "20-40K",
      "experience": "3-5年",
      "degree": "硕士",
      "company_name": "GE医疗",
      "company_logo": "https://img.bosszhipin.com/beijin/upload/com/workfeel/20230105/7bf6f160950405e90a424e449ee8b46cb96d599bd4df6a2a35fba5e1bb6535bd9f24cef225902919.jpg?x-oss-process=image/resize,w_100,limit_0",
      "company_kind": "医疗器械",
      "company_listing": "已上市",
      "company_size": "10000人以上",
      "boss_job": "",
      "key_words": [],
      "boss_active_time": "",
      "detail": ""
    },
    {
      "job_name": "数字电路设计工程师",
      "areaBusiness": "北京·大兴区·亦庄",
      "salary": "15-30K·13薪",
      "experience": "3-5年",
      "degree": "硕士",
      "company_name": "北京显芯科技有限公司",
      "company_logo": "https://img.bosszhipin.com/beijin/mcs/chatphoto/20200713/f2ac5b69677f7a5b2f67b6f6afacefea7c52c67b3f509c2b56ead80186d5f718_s.jpg?x-oss-process=image/resize,w_100,limit_0",
      "company_kind": "半导体/芯片",
      "company_listing": "B轮",
      "company_size": "20-99人",
      "boss_job": "",
      "key_words": [],
      "boss_active_time": "",
      "detail": ""
    },
    {
      "job_name": "AI产品经理",
      "areaBusiness": "北京·大兴区·亦庄",
      "salary": "18-25K",
      "experience": "3-5年",
      "degree": "硕士",
      "company_name": "京东集团",
      "company_logo": "https://img.bosszhipin.com/beijin/mcs/bar/20191129/3cdf5ba2149e309b38868b62ae9c22cabe1bd4a3bd2a63f070bdbdada9aad826.jpg?x-oss-process=image/resize,w_100,limit_0",
      "company_kind": "电子商务",
      "company_listing": "已上市",
      "company_size": "10000人以上",
      "boss_job": "",
      "key_words": [],
      "boss_active_time": "",
      "detail": ""
    }
  ]
}