{
  "experience": "104",
  "degree": "203",
  "areaBusiness": "110113",
  "total": 56,
  "catch_total": 56,
  "jobs": [
    {
      "job_name": "web前端",
      "areaBusiness": "北京·顺义区·后沙峪",
      "salary": "12-20K·13薪",
      "experience": "1-3年",
      "degree": "本科",
      "company_name": "康糖医疗",
      "company_logo": "https://img.bosszhipin.com/beijin/mcs/chatphoto/20190219/cfb9a9150a03f45dd4ea8f5d6093d2b5fccc04a1a7cd5d6c576181763351b724.jpg?x-oss-process=image/resize,w_100,limit_0",
      "company_kind": "医疗健康",
      "company_listing": "A轮",
      "company_size": "0-20人",
      "boss_job": "",
      "key_words": [],
      "boss_active_time": "",
      "detail": ""
    },
    {
      "job_name": "前端工程师",
      "areaBusiness": "北京·顺义区·后沙峪",
      "salary": "6-10K",
      "experience": "1-3年",
      "degree": "本科",
      "company_name": "优讯时代",
      "company_logo": "https://img.bosszhipin.com/beijin/mcs/chatphoto/20210326/8e42521d544aa92464c695f0d165c49ffc70fa1139a2ab1e81891c83826a267b_s.jpg?x-oss-process=image/resize,w_100,limit_0",
      "company_kind": "计算机软件",
      "company_listing": "未融资",
      "company_size": "100-499人",
      "boss_job": "",
      "key_words": [],
      "boss_active_time": "",
      "detail": ""
    },
    {
      "job_name": "前端工程师",
      "areaBusiness": "北京·顺义区·南彩",
      "salary": "5-7K",
      "experience": "1-3年",
      "degree": "本科",
      "company_name": "德森科技",
      "company_logo": "https://img.bosszhipin.com/beijin/mcs/chatphoto/20210511/adf9c835b88eef930bbee5fc4742df73b4e4a8ed0e329b8219734d3254cc40d5_s.jpg?x-oss-process=image/resize,w_100,limit_0",
      "company_kind": "运营商/增值服务",
      "company_listing": "不需要融资",
      "company_size": "20-99人",
      "boss_job": "",
      "key_words": [],
      "boss_active_time": "",
      "detail": ""
    },
    {
      "job_name": "前端工程师",
      "areaBusiness": "北京·顺义区·天竺",
      "salary": "10-15K",
      "experience": "1-3年",
      "degree": "本科",
      "company_name": "知因谱",
      "company_logo": "https://img.bosszhipin.com/beijin/upload/com/workfeel/20231011/7bf6f160950405e9daf991bec37a16890d95c8f299a843bfdf0ff8dd90c3d32b8c1017e3818d3f28.png.webp?x-oss-process=image/resize,w_100,limit_0",
      "company_kind": "学术/科研",
      "company_listing": "未融资",
      "company_size": "0-20人",
      "boss_job": "",
      "key_words": [],
      "boss_active_time": "",
      "detail": ""
    },
    {
      "job_name": "前端工程师",
      "areaBusiness": "北京·顺义区·李桥",
      "salary": "12-20K",
      "experience": "1-3年",
      "degree": "本科",
      "company_name": "奇云诺德",
      "company_logo": "https://img.bosszhipin.com/beijin/mcs/chatphoto/20190307/211267ce3a69cf0fe5c5f2d0366a1f961fab2f6693c28142ea5bd79f3158b533_s.jpg?x-oss-process=image/resize,w_100,limit_0",
      "company_kind": "医疗健康",
      "company_listing": "天使轮",
      "company_size": "20-99人",
      "boss_job": "",
      "key_words": [],
      "boss_active_time": "",
      "detail": ""
    },
    {
      "job_name": "前端开发工程师",
      "areaBusiness": "北京·顺义区·天竺",
      "salary": "10-15K",
      "experience": "1-3年",
      "degree": "本科",
      "company_name": "北京携门科技有限公司",
      "company_logo": "https://img.bosszhipin.com/beijin/icon/894ce6fa7e58d64d57e7f22d2f3a9d18afa7fcceaa24b8ea28f56f1bb14732c0.png?x-oss-process=image/resize,w_100,limit_0",
      "company_kind": "电子商务",
      "company_listing": "无阶段",
      "company_size": "20-99人",
      "boss_job": "",
      "key_words": [],
      "boss_active_time": "",
      "detail": ""
    },
    {
      "job_name": "前端开发工程师",
      "areaBusiness": "北京·顺义区·后沙峪",
      "salary": "4000-5000元/月",
      "experience": "1-3年",
      "degree": "本科",
      "company_name": "北京蓝仁东科技",
      "company_logo": "https://img.bosszhipin.com/beijin/icon/894ce6fa7e58d64d57e7f22d2f3a9d18afa7fcceaa24b8ea28f56f1bb14732c0.png?x-oss-process=image/resize,w_100,limit_0",
      "company_kind": "互联网",
      "company_listing": "不需要融资",
      "company_size": "0-20人",
      "boss_job": "",
      "key_words": [],
      "boss_active_time": "",
      "detail": ""
    },
    {
      "job_name": "web前端工程师",
      "areaBusiness": "北京·顺义区·光明",
      "salary": "8-12K",
      "experience": "1-3年",
      "degree": "本科",
      "company_name": "快虎",
      "company_logo": "https://img.bosszhipin.com/beijin/icon/894ce6fa7e58d64d57e7f22d2f3a9d18afa7fcceaa24b8ea28f56f1bb14732c0.png?x-oss-process=image/resize,w_100,limit_0",
      "company_kind": "企业服务",
      "company_listing": "不需要融资",
      "company_size": "0-20人",
      "boss_job": "",
      "key_words": [],
      "boss_active_time": "",
      "detail": ""
    },
    {
      "job_name": "网页前端工程师",
      "areaBusiness": "北京·顺义区·后沙峪",
      "salary": "10-11K",
      "experience": "1-3年",
      "degree": "本科",
      "company_name": "北京迪比西进出口",
      "company_logo": "https://img.bosszhipin.com/beijin/icon/894ce6fa7e58d64d57e7f22d2f3a9d18afa7fcceaa24b8ea28f56f1bb14732c0.png?x-oss-process=image/resize,w_100,limit_0",
      "company_kind": "食品/饮料/烟酒",
      "company_listing": "不需要融资",
      "company_size": "0-20人",
      "boss_job": "",
      "key_words": [],
      "boss_active_time": "",
      "detail": ""
    },
    {
      "job_name": "初级前端开发工程师",
      "areaBusiness": "北京·顺义区·马坡",
      "salary": "3-5K·13薪",
      "experience": "1-3年",
      "degree": "本科",
      "company_name": "麦进科技",
      "company_logo": "https://img.bosszhipin.com/beijin/icon/894ce6fa7e58d64d57e7f22d2f3a9d18afa7fcceaa24b8ea28f56f1bb14732c0.png?x-oss-process=image/resize,w_100,limit_0",
      "company_kind": "计算机软件",
      "company_listing": "未融资",
      "company_size": "0-20人",
      "boss_job": "",
      "key_words": [],
      "boss_active_time": "",
      "detail": ""
    },
    {
      "job_name": "前端开发工程师",
      "areaBusiness": "北京·顺义区·仁和",
      "salary": "10-13K·13薪",
      "experience": "1-3年",
      "degree": "本科",
      "company_name": "海威锐博",
      "company_logo": "https://img.bosszhipin.com/beijin/app/mobile/normal-0e3f1e4441a21d4874cece3a3d81f0fe.png?x-oss-process=image/resize,w_100,limit_0",
      "company_kind": "计算机软件",
      "company_listing": "无阶段",
      "company_size": "20-99人",
      "boss_job": "",
      "key_words": [],
      "boss_active_time": "",
      "detail": ""
    },
    {
      "job_name": "前端开发工程师-初级",
      "areaBusiness": "北京·顺义区·后沙峪",
      "salary": "11-18K·13薪",
      "experience": "1-3年",
      "degree": "本科",
      "company_name": "中航材导航技术",
      "company_logo": "https://img.bosszhipin.com/beijin/mcs/chatphoto/20181220/e5d843586c15903224b75da1d3daac38cfcd208495d565ef66e7dff9f98764da.jpg?x-oss-process=image/resize,w_100,limit_0",
      "company_kind": "计算机软件",
      "company_listing": "未融资",
      "company_size": "100-499人",
      "boss_job": "",
      "key_words": [],
      "boss_active_time": "",
      "detail": ""
    },
    {
      "job_name": "web前端开发工程师-上市公司+五险一金",
      "areaBusiness": "北京·顺义区·光明",
      "salary": "14-16K",
      "experience": "1-3年",
      "degree": "本科",
      "company_name": "屹通信息科技",
      "company_logo": "https://img.bosszhipin.com/beijin/mcs/chatphoto/20180827/781a69eb491aecdacb2f1b60ddc0ec79cfcd208495d565ef66e7dff9f98764da.jpg?x-oss-process=image/resize,w_100,limit_0",
      "company_kind": "计算机软件",
      "company_listing": "已上市",
      "company_size": "1000-9999人",
      "boss_job": "",
      "key_words": [],
      "boss_active_time": "",
      "detail": ""
    },
    {
      "job_name": "前端开发工程师",
      "areaBusiness": "北京·顺义区·马坡",
      "salary": "20-40K·14薪",
      "experience": "1-3年",
      "degree": "本科",
      "company_name": "理想汽车",
      "company_logo": "https://img.bosszhipin.com/beijin/mcs/banner/2562e3a83b2c2a3cfa0c9316a90e2c07cfcd208495d565ef66e7dff9f98764da.png?x-oss-process=image/resize,w_100,limit_0",
      "company_kind": "智能硬件",
      "company_listing": "已上市",
      "company_size": "10000人以上",
      "boss_job": "",
      "key_words": [],
      "boss_active_time": "",
      "detail": ""
    },
    {
      "job_name": "GIS开发工程师（前端开发）",
      "areaBusiness": "北京·顺义区·首都机场",
      "salary": "7-12K",
      "experience": "1-3年",
      "degree": "本科",
      "company_name": "中色蓝图",
      "company_logo": "https://img.bosszhipin.com/beijin/icon/894ce6fa7e58d64d57e7f22d2f3a9d18afa7fcceaa24b8ea28f56f1bb14732c0.png?x-oss-process=image/resize,w_100,limit_0",
      "company_kind": "其他生活服务",
      "company_listing": "无阶段",
      "company_size": "500-999人",
      "boss_job": "",
      "key_words": [],
      "boss_active_time": "",
      "detail": ""
    },
    {
      "job_name": "软件开发工程师",
      "areaBusiness": "北京·顺义区·后沙峪",
      "salary": "9-14K·13薪",
      "experience": "1-3年",
      "degree": "本科",
      "company_name": "正印科技",
      "company_logo": "https://img.bosszhipin.com/beijin/mcs/chatphoto/20180512/89946d8742f4cd27581af20443df631b88fa863d10a9834ff720cfe8b74b6d82.jpg?x-oss-process=image/resize,w_100,limit_0",
      "company_kind": "仪器仪表",
      "company_listing": "未融资",
      "company_size": "20-99人",
      "boss_job": "",
      "key_words": [],
      "boss_active_time": "",
      "detail": ""
    },
    {
      "job_name": "全栈开发工程师",
      "areaBusiness": "北京·顺义区·李桥",
      "salary": "18-20K",
      "experience": "1-3年",
      "degree": "本科",
      "company_name": "中科星图",
      "company_logo": "https://img.bosszhipin.com/beijin/upload/com/workfeel/20241113/7bf6f160950405e98117bc6d0670c33bbb255f7ed1d80842a2a58023028395b32408a96ef86947c4.png.webp?x-oss-process=image/resize,w_100,limit_0",
      "company_kind": "计算机软件",
      "company_listing": "已上市",
      "company_size": "1000-9999人",
      "boss_job": "",
      "key_words": [],
      "boss_active_time": "",
      "detail": ""
    },
    {
      "job_name": ".NET 开发工程师",
      "areaBusiness": "北京·顺义区·南法信",
      "salary": "8-10K",
      "experience": "1-3年",
      "degree": "本科",
      "company_name": "嘉途",
      "company_logo": "https://img.bosszhipin.com/beijin/app/mobile/normal-0e3f1e4441a21d4874cece3a3d81f0fe.png?x-oss-process=image/resize,w_100,limit_0",
      "company_kind": "互联网",
      "company_listing": "无阶段",
      "company_size": "0-20人",
      "boss_job": "",
      "key_words": [],
      "boss_active_time": "",
      "detail": ""
    },
    {
      "job_name": "云平台开发工程师",
      "areaBusiness": "北京·顺义区·马坡",
      "salary": "20-35K·13薪",
      "experience": "1-3年",
      "degree": "本科",
      "company_name": "民生科技",
      "company_logo": "https://img.bosszhipin.com/beijin/mcs/chatphoto/20180810/78175356acc0711bc8768691901031f98231e2e68234e5f3472e469d7b2168a5.jpg?x-oss-process=image/resize,w_100,limit_0",
      "company_kind": "互联网金融",
      "company_listing": "不需要融资",
      "company_size": "1000-9999人",
      "boss_job": "",
      "key_words": [],
      "boss_active_time": "",
      "detail": ""
    },
    {
      "job_name": "网络安全工程师培训讲师",
      "areaBusiness": "北京·顺义区·天竺",
      "salary": "13-20K",
      "experience": "1-3年",
      "degree": "本科",
      "company_name": "长者福祉教育",
      "company_logo": "https://img.bosszhipin.com/beijin/app/mobile/normal-0e3f1e4441a21d4874cece3a3d81f0fe.png?x-oss-process=image/resize,w_100,limit_0",
      "company_kind": "培训/辅导机构",
      "company_listing": "未融资",
      "company_size": "20-99人",
      "boss_job": "",
      "key_words": [],
      "boss_active_time": "",
      "detail": ""
    },
    {
      "job_name": "Java开发工程师",
      "areaBusiness": "北京·顺义区·马坡",
      "salary": "7-12K",
      "experience": "1-3年",
      "degree": "本科",
      "company_name": "天创科林科技有限公司",
      "company_logo": "https://img.bosszhipin.com/beijin/mcs/chatphoto/20161123/ea7ae6a480f6fd73b9a35bf78ec26015fcd5c92fa02f9d6e864ab9aa6abacc71.jpg?x-oss-process=image/resize,w_100,limit_0",
      "company_kind": "计算机软件",
      "company_listing": "不需要融资",
      "company_size": "20-99人",
      "boss_job": "",
      "key_words": [],
      "boss_active_time": "",
      "detail": ""
    },
    {
      "job_name": "python web全栈工程师",
      "areaBusiness": "北京·顺义区·天竺",
      "salary": "10-15K",
      "experience": "1-3年",
      "degree": "本科",
      "company_name": "泰星达",
      "company_logo": "https://c-res.zhipin.com/jrs/645c48b8a235bbd66e69811b2e86e16f.jpg?x-oss-process=image/resize,w_100,limit_0",
      "company_kind": "电子/硬件开发",
      "company_listing": "天使轮",
      "company_size": "20-99人",
      "boss_job": "",
      "key_words": [],
      "boss_active_time": "",
      "detail": ""
    },
    {
      "job_name": "Java后端开发工程师",
      "areaBusiness": "北京·顺义区·马坡",
      "salary": "10-15K",
      "experience": "1-3年",
      "degree": "本科",
      "company_name": "靠前品牌策划",
      "company_logo": "https://img.bosszhipin.com/beijin/icon/894ce6fa7e58d64d57e7f22d2f3a9d18afa7fcceaa24b8ea28f56f1bb14732c0.png?x-oss-process=image/resize,w_100,limit_0",
      "company_kind": "广告/公关/会展",
      "company_listing": "无阶段",
      "company_size": "0-20人",
      "boss_job": "",
      "key_words": [],
      "boss_active_time": "",
      "detail": ""
    },
    {
      "job_name": "PHP开发工程师",
      "areaBusiness": "北京·顺义区·后沙峪",
      "salary": "18-22K",
      "experience": "1-3年",
      "degree": "本科",
      "company_name": "中际华科",
      "company_logo": "https://img.bosszhipin.com/beijin/mcs/banner/20180310/0f2ef5140160425fd989d87ead17cc9d33d208e8d6fc287973c46e5cb5346f06.png?x-oss-process=image/resize,w_100,limit_0",
      "company_kind": "企业服务",
      "company_listing": "无阶段",
      "company_size": "0-20人",
      "boss_job": "",
      "key_words": [],
      "boss_active_time": "",
      "detail": ""
    },
    {
      "job_name": "java开发工程师",
      "areaBusiness": "北京·顺义区·李桥",
      "salary": "12-20K",
      "experience": "1-3年",
      "degree": "本科",
      "company_name": "银景科技",
      "company_logo": "https://img.bosszhipin.com/beijin/mcs/chatphoto/20190412/4b8c85a7811952d273266592e22a944edb01bfa075e15932b46291478a5aa6aa.jpg?x-oss-process=image/resize,w_100,limit_0",
      "company_kind": "计算机软件",
      "company_listing": "未融资",
      "company_size": "20-99人",
      "boss_job": "",
      "key_words": [],
      "boss_active_time": "",
      "detail": ""
    },
    {
      "job_name": "中级java工程师",
      "areaBusiness": "北京·顺义区·石园",
      "salary": "10-15K",
      "experience": "1-3年",
      "degree": "本科",
      "company_name": "炎黄鸿泰",
      "company_logo": "https://img.bosszhipin.com/beijin/mcs/chatphoto/20190321/8493e3adbb9c2e206dd0fa2ff009a1bb22d4b71cbac1beaf71aabed3bac92ffc.png?x-oss-process=image/resize,w_100,limit_0",
      "company_kind": "计算机软件",
      "company_listing": "未融资",
      "company_size": "20-99人",
      "boss_job": "",
      "key_words": [],
      "boss_active_time": "",
      "detail": ""
    },
    {
      "job_name": "全栈工程师",
      "areaBusiness": "北京·顺义区·后沙峪",
      "salary": "13-18K",
      "experience": "1-3年",
      "degree": "本科",
      "company_name": "民航东北凯亚",
      "company_logo": "https://img.bosszhipin.com/beijin/upload/com/workfeel/20210708/52c77e1d0c2fb5b7a50f7ce4afade37815dd2ad49cd30096b68e1ba8221ead3a.jpg?x-oss-process=image/resize,w_100,limit_0",
      "company_kind": "分类信息",
      "company_listing": "不需要融资",
      "company_size": "100-499人",
      "boss_job": "",
      "key_words": [],
      "boss_active_time": "",
      "detail": ""
    },
    {
      "job_name": "java源代码审计工程师",
      "areaBusiness": "北京·顺义区·马坡",
      "salary": "10-15K·13薪",
      "experience": "1-3年",
      "degree": "本科",
      "company_name": "国舜股份",
      "company_logo": "https://img.bosszhipin.com/beijin/mcs/chatphoto/20160428/faf777d1753452fd8a3ec73e68413bf8eac67528bdb5b16e3f91a450c187a017.jpg?x-oss-process=image/resize,w_100,limit_0",
      "company_kind": "信息安全",
      "company_listing": "已上市",
      "company_size": "100-499人",
      "boss_job": "",
      "key_words": [],
      "boss_active_time": "",
      "detail": ""
    },
    {
      "job_name": "兼职cocos游戏开发",
      "areaBusiness": "北京·顺义区·中央别墅区",
      "salary": "200-400元/天",
      "experience": "1-3年",
      "degree": "本科",
      "company_name": "快海智投",
      "company_logo": "https://img.bosszhipin.com/beijin/upload/com/workfeel/20220110/7bf6f160950405e9ede40b6cf3475c5dfad68166fa6ac83cbc94ec41ad3115a16991340251bbbe6b.jpg?x-oss-process=image/resize,w_100,limit_0",
      "company_kind": "互联网",
      "company_listing": "不需要融资",
      "company_size": "20-99人",
      "boss_job": "",
      "key_words": [],
      "boss_active_time": "",
      "detail": ""
    },
    {
      "job_name": "益智游戏与平台产品经理",
      "areaBusiness": "北京·顺义区·天竺",
      "salary": "10-11K",
      "experience": "1-3年",
      "degree": "本科",
      "company_name": "大屋文创",
      "company_logo": "https://img.bosszhipin.com/beijin/upload/com/logo/20210913/7b5b554d84f9729c7ef387992d0be828323c560bd3e0314786d5846f4d8f3ffbc3499c1ca49c2a94.png?x-oss-process=image/resize,w_100,limit_0",
      "company_kind": "文化艺术/娱乐",
      "company_listing": "未融资",
      "company_size": "0-20人",
      "boss_job": "",
      "key_words": [],
      "boss_active_time": "",
      "detail": ""
    },
    {
      "job_name": "ETL工程师",
      "areaBusiness": "北京·顺义区·马坡",
      "salary": "8-12K·13薪",
      "experience": "1-3年",
      "degree": "本科",
      "company_name": "邦克佳软",
      "company_logo": "https://img.bosszhipin.com/beijin/icon/894ce6fa7e58d64d57e7f22d2f3a9d18afa7fcceaa24b8ea28f56f1bb14732c0.png?x-oss-process=image/resize,w_100,limit_0",
      "company_kind": "计算机软件",
      "company_listing": "不需要融资",
      "company_size": "20-99人",
      "boss_job": "",
      "key_words": [],
      "boss_active_time": "",
      "detail": ""
    },
    {
      "job_name": "全职少儿英语老师",
      "areaBusiness": "北京·顺义区·后沙峪",
      "salary": "7-12K",
      "experience": "1-3年",
      "degree": "本科",
      "company_name": "中视国利培训学校",
      "company_logo": "https://img.bosszhipin.com/beijin/upload/com/logo/20241007/7b5b554d84f9729c8a9866841777f14debd18741c7fe48849d0a140641364e19d219eeb5d0818408.jpg.webp?x-oss-process=image/resize,w_100,limit_0",
      "company_kind": "培训/辅导机构",
      "company_listing": "不需要融资",
      "company_size": "100-499人",
      "boss_job": "",
      "key_words": [],
      "boss_active_time": "",
      "detail": ""
    },
    {
      "job_name": "物流单证员",
      "areaBusiness": "北京·顺义区·后沙峪",
      "salary": "8-10K·14薪",
      "experience": "1-3年",
      "degree": "本科",
      "company_name": "康纳克斯",
      "company_logo": "https://img.bosszhipin.com/beijin/upload/com/workfeel/20210708/6bf83a899558d9e55771f72463a3bfe98db3065ba02837ec4f0d52cc3a267074.jpg?x-oss-process=image/resize,w_100,limit_0",
      "company_kind": "石油/石化",
      "company_listing": "未融资",
      "company_size": "20-99人",
      "boss_job": "",
      "key_words": [],
      "boss_active_time": "",
      "detail": ""
    },
    {
      "job_name": "C++",
      "areaBusiness": "北京·顺义区·李桥",
      "salary": "10-15K",
      "experience": "1-3年",
      "degree": "本科",
      "company_name": "正元地理信息",
      "company_logo": "https://img.bosszhipin.com/beijin/mcs/chatphoto/20210311/5ad7747bdc73728d6a182f831babd227e8edfdbfd4349768956e0862320ad775_s.jpg?x-oss-process=image/resize,w_100,limit_0",
      "company_kind": "计算机软件",
      "company_listing": "已上市",
      "company_size": "1000-9999人",
      "boss_job": "",
      "key_words": [],
      "boss_active_time": "",
      "detail": ""
    },
    {
      "job_name": "UI设计师",
      "areaBusiness": "北京·顺义区",
      "salary": "5-8K",
      "experience": "1-3年",
      "degree": "本科",
      "company_name": "联信通达科技发",
      "company_logo": "https://img.bosszhipin.com/beijin/mcs/chatphoto/20160928/aded0768f6ff03fce6a7f53f9fe35a311c032688a05ce76487b819ce60d6711f.jpg?x-oss-process=image/resize,w_100,limit_0",
      "company_kind": "计算机软件",
      "company_listing": "不需要融资",
      "company_size": "20-99人",
      "boss_job": "",
      "key_words": [],
      "boss_active_time": "",
      "detail": ""
    },
    {
      "job_name": "视频剪辑 平面设计",
      "areaBusiness": "北京·顺义区·后沙峪",
      "salary": "7-10K",
      "experience": "1-3年",
      "degree": "本科",
      "company_name": "9930生物技术",
      "company_logo": "https://img.bosszhipin.com/beijin/upload/com/logo/20240415/7b5b554d84f9729ca59d8a6d1a6d8dafde45da5de274b9c9336dd1cc9e8a4aaeadccaf8fbc901156.jpg.webp?x-oss-process=image/resize,w_100,limit_0",
      "company_kind": "生物/制药",
      "company_listing": "不需要融资",
      "company_size": "20-99人",
      "boss_job": "",
      "key_words": [],
      "boss_active_time": "",
      "detail": ""
    },
    {
      "job_name": "移动端应用架构师（Andriod/IOS）",
      "areaBusiness": "北京·顺义区·马坡",
      "salary": "10-15K",
      "experience": "1-3年",
      "degree": "本科",
      "company_name": "比尔北京",
      "company_logo": "https://img.bosszhipin.com/beijin/mcs/chatphoto/20200918/381d396fb473d392409f92073b4cd55e62187f28318474e8199a0d235f2123f6_s.jpg?x-oss-process=image/resize,w_100,limit_0",
      "company_kind": "计算机软件",
      "company_listing": "未融资",
      "company_size": "0-20人",
      "boss_job": "",
      "key_words": [],
      "boss_active_time": "",
      "detail": ""
    },
    {
      "job_name": "项目实施工程师",
      "areaBusiness": "北京·顺义区·天竺",
      "salary": "8-13K",
      "experience": "1-3年",
      "degree": "本科",
      "company_name": "泛微网络",
      "company_logo": "https://img.bosszhipin.com/beijin/mcs/banner/edc62c90326b3e9fb3638ee874f5ba44cfcd208495d565ef66e7dff9f98764da.jpg?x-oss-process=image/resize,w_100,limit_0",
      "company_kind": "计算机软件",
      "company_listing": "已上市",
      "company_size": "1000-9999人",
      "boss_job": "",
      "key_words": [],
      "boss_active_time": "",
      "detail": ""
    },
    {
      "job_name": "JAVA开发-银行项目-需出差",
      "areaBusiness": "北京·顺义区·仁和",
      "salary": "9-12K",
      "experience": "1-3年",
      "degree": "本科",
      "company_name": "安硕信息",
      "company_logo": "https://img.bosszhipin.com/beijin/mcs/chatphoto/20160507/206e7951a40108408bcf6778dfbe628c37550262a44a166f55ecb9d258666882.jpg?x-oss-process=image/resize,w_100,limit_0",
      "company_kind": "计算机软件",
      "company_listing": "已上市",
      "company_size": "1000-9999人",
      "boss_job": "",
      "key_words": [],
      "boss_active_time": "",
      "detail": ""
    },
    {
      "job_name": "高底薪+管理储备+B端餐饮硬件MJ001297",
      "areaBusiness": "北京·顺义区·天竺",
      "salary": "10-15K",
      "experience": "1-3年",
      "degree": "本科",
      "company_name": "厨芯",
      "company_logo": "https://img.bosszhipin.com/beijin/mcs/chatphoto/20200521/6d81bab2559d4664b9fc8ae558048ae571106aa07d5fb3ce0ebe3fd740180c3f_s.jpg?x-oss-process=image/resize,w_100,limit_0",
      "company_kind": "智能硬件",
      "company_listing": "D轮及以上",
      "company_size": "1000-9999人",
      "boss_job": "",
      "key_words": [],
      "boss_active_time": "",
      "detail": ""
    },
    {
      "job_name": "前端工程师",
      "areaBusiness": "北京·顺义区·南彩",
      "salary": "5-7K",
      "experience": "1-3年",
      "degree": "本科",
      "company_name": "德森科技",
      "company_logo": "https://img.bosszhipin.com/beijin/mcs/chatphoto/20210511/adf9c835b88eef930bbee5fc4742df73b4e4a8ed0e329b8219734d3254cc40d5_s.jpg?x-oss-process=image/resize,w_100,limit_0",
      "company_kind": "运营商/增值服务",
      "company_listing": "不需要融资",
      "company_size": "20-99人",
      "boss_job": "",
      "key_words": [],
      "boss_active_time": "",
      "detail": ""
    },
    {
      "job_name": "JavaScript高级工程师",
      "areaBusiness": "北京·顺义区·光明",
      "salary": "8-12K",
      "experience": "1-3年",
      "degree": "本科",
      "company_name": "快虎",
      "company_logo": "https://img.bosszhipin.com/beijin/icon/894ce6fa7e58d64d57e7f22d2f3a9d18afa7fcceaa24b8ea28f56f1bb14732c0.png?x-oss-process=image/resize,w_100,limit_0",
      "company_kind": "企业服务",
      "company_listing": "不需要融资",
      "company_size": "0-20人",
      "boss_job": "",
      "key_words": [],
      "boss_active_time": "",
      "detail": ""
    },
    {
      "job_name": "java开发工程师",
      "areaBusiness": "北京·顺义区·后沙峪",
      "salary": "6-10K",
      "experience": "1-3年",
      "degree": "本科",
      "company_name": "优讯时代",
      "company_logo": "https://img.bosszhipin.com/beijin/mcs/chatphoto/20210326/8e42521d544aa92464c695f0d165c49ffc70fa1139a2ab1e81891c83826a267b_s.jpg?x-oss-process=image/resize,w_100,limit_0",
      "company_kind": "计算机软件",
      "company_listing": "未融资",
      "company_size": "100-499人",
      "boss_job": "",
      "key_words": [],
      "boss_active_time": "",
      "detail": ""
    },
    {
      "job_name": "Node.js",
      "areaBusiness": "北京·顺义区·后沙峪",
      "salary": "12-22K·13薪",
      "experience": "1-3年",
      "degree": "本科",
      "company_name": "康糖医疗",
      "company_logo": "https://img.bosszhipin.com/beijin/mcs/chatphoto/20190219/cfb9a9150a03f45dd4ea8f5d6093d2b5fccc04a1a7cd5d6c576181763351b724.jpg?x-oss-process=image/resize,w_100,limit_0",
      "company_kind": "医疗健康",
      "company_listing": "A轮",
      "company_size": "0-20人",
      "boss_job": "",
      "key_words": [],
      "boss_active_time": "",
      "detail": ""
    },
    {
      "job_name": "产品外包/外援 GPT产品",
      "areaBusiness": "北京·顺义区·马坡",
      "salary": "23-24K",
      "experience": "1-3年",
      "degree": "本科",
      "company_name": "理想汽车",
      "company_logo": "https://img.bosszhipin.com/beijin/mcs/banner/2562e3a83b2c2a3cfa0c9316a90e2c07cfcd208495d565ef66e7dff9f98764da.png?x-oss-process=image/resize,w_100,limit_0",
      "company_kind": "智能硬件",
      "company_listing": "已上市",
      "company_size": "10000人以上",
      "boss_job": "",
      "key_words": [],
      "boss_active_time": "",
      "detail": ""
    },
    {
      "job_name": "后端开发工程师",
      "areaBusiness": "北京·顺义区·首都机场",
      "salary": "7-12K",
      "experience": "1-3年",
      "degree": "本科",
      "company_name": "中色蓝图",
      "company_logo": "https://img.bosszhipin.com/beijin/icon/894ce6fa7e58d64d57e7f22d2f3a9d18afa7fcceaa24b8ea28f56f1bb14732c0.png?x-oss-process=image/resize,w_100,limit_0",
      "company_kind": "其他生活服务",
      "company_listing": "无阶段",
      "company_size": "500-999人",
      "boss_job": "",
      "key_words": [],
      "boss_active_time": "",
      "detail": ""
    },
    {
      "job_name": "小学高级英语教师",
      "areaBusiness": "北京·顺义区·天竺",
      "salary": "5-10K",
      "experience": "1-3年",
      "degree": "本科",
      "company_name": "中视国利培训学校",
      "company_logo": "https://img.bosszhipin.com/beijin/upload/com/logo/20241007/7b5b554d84f9729c8a9866841777f14debd18741c7fe48849d0a140641364e19d219eeb5d0818408.jpg.webp?x-oss-process=image/resize,w_100,limit_0",
      "company_kind": "培训/辅导机构",
      "company_listing": "不需要融资",
      "company_size": "100-499人",
      "boss_job": "",
      "key_words": [],
      "boss_active_time": "",
      "detail": ""
    },
    {
      "job_name": "GIS开发工程师",
      "areaBusiness": "北京·顺义区·首都机场",
      "salary": "13-25K",
      "experience": "1-3年",
      "degree": "本科",
      "company_name": "正元地理信息",
      "company_logo": "https://img.bosszhipin.com/beijin/mcs/chatphoto/20210311/5ad7747bdc73728d6a182f831babd227e8edfdbfd4349768956e0862320ad775_s.jpg?x-oss-process=image/resize,w_100,limit_0",
      "company_kind": "计算机软件",
      "company_listing": "已上市",
      "company_size": "1000-9999人",
      "boss_job": "",
      "key_words": [],
      "boss_active_time": "",
      "detail": ""
    },
    {
      "job_name": "python开发工程师",
      "areaBusiness": "北京·顺义区·后沙峪",
      "salary": "7-12K·13薪",
      "experience": "1-3年",
      "degree": "本科",
      "company_name": "正印科技",
      "company_logo": "https://img.bosszhipin.com/beijin/mcs/chatphoto/20180512/89946d8742f4cd27581af20443df631b88fa863d10a9834ff720cfe8b74b6d82.jpg?x-oss-process=image/resize,w_100,limit_0",
      "company_kind": "仪器仪表",
      "company_listing": "未融资",
      "company_size": "20-99人",
      "boss_job": "",
      "key_words": [],
      "boss_active_time": "",
      "detail": ""
    },
    {
      "job_name": "全栈工程师",
      "areaBusiness": "北京·顺义区·后沙峪",
      "salary": "15-20K·13薪",
      "experience": "1-3年",
      "degree": "本科",
      "company_name": "康糖医疗",
      "company_logo": "https://img.bosszhipin.com/beijin/mcs/chatphoto/20190219/cfb9a9150a03f45dd4ea8f5d6093d2b5fccc04a1a7cd5d6c576181763351b724.jpg?x-oss-process=image/resize,w_100,limit_0",
      "company_kind": "医疗健康",
      "company_listing": "A轮",
      "company_size": "0-20人",
      "boss_job": "",
      "key_words": [],
      "boss_active_time": "",
      "detail": ""
    },
    {
      "job_name": "地理信息系统开发工程师",
      "areaBusiness": "北京·顺义区·首都机场",
      "salary": "7-12K",
      "experience": "1-3年",
      "degree": "本科",
      "company_name": "中色蓝图",
      "company_logo": "https://img.bosszhipin.com/beijin/icon/894ce6fa7e58d64d57e7f22d2f3a9d18afa7fcceaa24b8ea28f56f1bb14732c0.png?x-oss-process=image/resize,w_100,limit_0",
      "company_kind": "其他生活服务",
      "company_listing": "无阶段",
      "company_size": "500-999人",
      "boss_job": "",
      "key_words": [],
      "boss_active_time": "",
      "detail": ""
    },
    {
      "job_name": "node.js后端开发工程师",
      "areaBusiness": "北京·顺义区·后沙峪",
      "salary": "15-22K·13薪",
      "experience": "1-3年",
      "degree": "本科",
      "company_name": "康糖医疗",
      "company_logo": "https://img.bosszhipin.com/beijin/mcs/chatphoto/20190219/cfb9a9150a03f45dd4ea8f5d6093d2b5fccc04a1a7cd5d6c576181763351b724.jpg?x-oss-process=image/resize,w_100,limit_0",
      "company_kind": "医疗健康",
      "company_listing": "A轮",
      "company_size": "0-20人",
      "boss_job": "",
      "key_words": [],
      "boss_active_time": "",
      "detail": ""
    },
    {
      "job_name": "GIS开发工程师",
      "areaBusiness": "北京·顺义区·首都机场",
      "salary": "7-12K",
      "experience": "1-3年",
      "degree": "本科",
      "company_name": "中色蓝图",
      "company_logo": "https://img.bosszhipin.com/beijin/icon/894ce6fa7e58d64d57e7f22d2f3a9d18afa7fcceaa24b8ea28f56f1bb14732c0.png?x-oss-process=image/resize,w_100,limit_0",
      "company_kind": "其他生活服务",
      "company_listing": "无阶段",
      "company_size": "500-999人",
      "boss_job": "",
      "key_words": [],
      "boss_active_time": "",
      "detail": ""
    },
    {
      "job_name": "后端开发工程师",
      "areaBusiness": "北京·顺义区·天竺",
      "salary": "12-22K",
      "experience": "1-3年",
      "degree": "本科",
      "company_name": "康糖医疗",
      "company_logo": "https://img.bosszhipin.com/beijin/mcs/chatphoto/20190219/cfb9a9150a03f45dd4ea8f5d6093d2b5fccc04a1a7cd5d6c576181763351b724.jpg?x-oss-process=image/resize,w_100,limit_0",
      "company_kind": "医疗健康",
      "company_listing": "A轮",
      "company_size": "0-20人",
      "boss_job": "",
      "key_words": [],
      "boss_active_time": "",
      "detail": ""
    },
    {
      "job_name": "Nodejs开发工程师",
      "areaBusiness": "北京·顺义区·首都机场",
      "salary": "7-12K",
      "experience": "1-3年",
      "degree": "本科",
      "company_name": "中色蓝图",
      "company_logo": "https://img.bosszhipin.com/beijin/icon/894ce6fa7e58d64d57e7f22d2f3a9d18afa7fcceaa24b8ea28f56f1bb14732c0.png?x-oss-process=image/resize,w_100,limit_0",
      "company_kind": "其他生活服务",
      "company_listing": "无阶段",
      "company_size": "500-999人",
      "boss_job": "",
      "key_words": [],
      "boss_active_time": "",
      "detail": ""
    },
    {
      "job_name": "Node.js",
      "areaBusiness": "北京·顺义区·后沙峪",
      "salary": "15-25K·13薪",
      "experience": "1-3年",
      "degree": "本科",
      "company_name": "康糖医疗",
      "company_logo": "https://img.bosszhipin.com/beijin/mcs/chatphoto/20190219/cfb9a9150a03f45dd4ea8f5d6093d2b5fccc04a1a7cd5d6c576181763351b724.jpg?x-oss-process=image/resize,w_100,limit_0",
      "company_kind": "医疗健康",
      "company_listing": "A轮",
      "company_size": "0-20人",
      "boss_job": "",
      "key_words": [],
      "boss_active_time": "",
      "detail": ""
    }
  ]
}